Workbook

Sheet Read me
B2: AI business case model
B3: Companion to the AI Engineering Playbook, section 12
B4: v1.0, August 2026
B6: About | C6: The business case model accompanying section 12 of the AI Engineering Playbook. Simplified and directional: it shows the shape and scale of the case, and a proper plan would carry more parameters and take more factors into account. Inputs holds the cost parameters, Scenarios the capacity and conversion grid, Model the three-year sums and Bridge the year-2 value waterfall.
B8: How to read it | C8: Blue cells are inputs. All figures in GBP thousands unless the units column says otherwise.
B10: Starting defaults | C10: Every input is a starting default, not a benchmark: the definitions column says what each one means and what evidence should move it. Anchors from published sources are quoted in their native currency (mostly USD), with GBP equivalents.
B12: Four cautions | C12: Freed capacity and conversion decide the case. Conversion is owned by the executive committee rather than any single leader, and the only benchmark that matters is your own section 9 ledger. Value is priced in loaded engineering cost, a payroll-equivalent measure rather than cash, EBITDA or recognised financial benefit: what finance recognises depends on the conversion route, as section 12 sets out. Year one is negative in every scenario by design, with costs landing ahead of the value ramp. And year 3 holds year-2 rates by default, an assumption that should be challenged.
B14: Scope and money | C14: All figures are in today's money, with nothing discounted. Holding everything in current terms cancels inflation and pay rises, and a real cost of capital would pull the Mid breakeven toward the year-2 to year-3 boundary. The model prices a functioning programme from the section 11 go decision. Year 1 can still go negative in the field, which is what the Phase 1 pilot and the gates are there to catch before scale. Any Phase 0 work to reach the engineering floor is assumed complete and funded outside this model, unless you price it in the optional Phase 0 input (0 by default).
B16: Playbook | C16: https://yspbob.github.io/AI-Playbook/AI_Engineering_Playbook.html
B20: Freed-capacity Conversion Route | C20: Recognised by finance
B21: Reduced contractor spend | C21: Direct cost reduction
B22: Avoided hiring | C22: Avoided future cost for hires that were already budgeted
B23: Additional delivery | C23: Incremental margin, earlier market entry, or both
B24: Quality and risk | C24: Verified avoided cost, plus quality effects that show up in client retention
B25: Debt paydown | C25: Booked later, as the velocity and incident gains it produces are measured
... B28: Authorship | C28: The playbook's closing section, How this playbook was made, covers the authorship and composition of the whole set.

Sheet Inputs
B2: Parameter | C2: Value | D2: Units | E2: Definition | F2: Benchmark and source | G2: Recalibrated by
B3: Engineers | C3: 300 | D3: FTE | E3: Engineering headcount in scope: single delivery system, scored and rolled out together (section 10). | F3: Playbook target readership 300-500. | G3: The section 10 scoping rule: score per delivery system.
B4: Blended fully-loaded cost per engineer | C4: 160 | D4: k/year | E4: Salary + employer taxes + benefits + overhead. | F4: London fully-loaded range about 120-180: Morgan McKinley UK 2026 base ranges, loaded at about +30% (BLS). | G4: Your own comp data, annually.
B5: FX rate (£ to $) | C5: 1.25 | D5: $/£ | E5: Bridge for USD-published anchors, used by USD-anchored formulas such as tooling. | G5: FX at each review.
B6: Tooling, all-in per developer-month | C6: =400/C5 -> 320 | D6: £/dev-month | E6: Seats + tokens + usage, averaged across the estate. | F6: USD 200-600 all-in (DX pricing survey). | G6: Gateway spend telemetry (section 6), quarterly.
B7: Year-1 tooling coverage, average % | C7: 60 | D7: % | E7: Average share of engineers with active tooling across year 1, as adoption waves land. Applies to the tooling and platform lines only. Year 2 onward runs at full coverage. | F7: A linear ramp to full coverage by year end averages about 50%. Set above it for the pilot's heavier token burn. | G7: Wave schedule actuals (section 11).
B8: Enabling team, % (build and rollout) | C8: 3 | D8: % | E8: Share of the engineering headcount through year 1. The team is additional to the engineers in scope: to model redeployment instead, reduce the engineers input by the same heads. | F8: DX benchmark: 2-6% of engineering headcount. The rate through build and rollout, before the steady-state floor below applies. | G8: DX benchmark refresh, annually.
B9: Enabling team, steady-state % | C9: 2 | D9: % | E9: Floor once rollout completes: per-team support and curriculum upkeep only. Applies from year 2, when the last wave lands (section 11). | F9: Bottom of the DX 2-6% band: the build work ends with the rollout. | G9: Section 7 sizing at each wave.
B10: Platform monthly run cost | C10: 6 | D10: k/month | E10: The monthly cost of the AI-specific platform layer. | G10: Actual invoices, quarterly.
B11: Platform stack | C11: =C10*12 -> 72 | D11: k/year | E11: AI tooling only: gateway, observability, retrieval and eval infrastructure, excluding tokens. Usage-priced, not per seat. Baseline platform (developer portal, CI/CD) is assumed in place and excluded. | F11: £10-75k/yr for this org size: playbook aggregation over Langfuse, Portkey and LiteLLM pricing, Aug 2026. Published tiers reach about £43k, the rest is estimated enterprise pricing. | G11: Actual invoices, quarterly.
B12: Training and hidden, year 1 | C12: 1.7 | D12: k/eng/yr | E12: Cash costs only: external facilitation, courseware and year-one compliance work. A starting default above the ATD steady-state average. Time costs sit in net gain and the year-one dip, trainer labour in the enabling team row. | F12: No published year-one benchmark exists. ATD steady-state is about £840 per employee, and year one adds external facilitation and one-off compliance work, so the default sits at roughly double the steady-state rate. | G12: Actual programme spend as invoices land.
B13: Training and hidden, ongoing | C13: 0.8 | D13: k/eng/yr | E13: Cash costs once the programme runs on internal muscle: materials, refreshers and routine compliance. | F13: Anchored on the ATD average. | G13: Your actual spend, from quarter one.
B14: Instability adjustment | C14: 0 | D14: k/year | E14: Optional: cost of a change-failure-rate rise (DORA mechanics: deploys x CFR delta x recovery hours x cost per hour). Zero switches it off. | F14: DORA ROI report models this line explicitly. | G14: CFR movement in section 8 telemetry.
B15: Phase 0 remediation, one-off | C15: 0 | D15: k | E15: Optional: legacy clean-up required to reach the engineering floor before the programme starts. Zero by default. | F15: No benchmark, entirely company-specific | G15: The section 10 readiness scores, priced.

Sheet Scenarios
B2: Capacity freed: the engineer time AI frees after its own overheads, as a share of all engineer time. Conversion: the share of that freed capacity you actually pick up and book as value (section 9). Captured = freed x conversion, the value the model books.
C4: Year 1 Capacity Gains | F4: Year 2 Capacity Gains | I4: Year 3 Capacity Gains
B5: Scenario | C5: Freed | D5: Converted | E5: Captured | F5: Freed | G5: Converted | H5: Captured | I5: Freed | J5: Converted | K5: Captured
B6: Low | C6: 0.05 | D6: 0.4 | E6: =D6*C6 -> 0.02 | F6: 0.08 | G6: 0.7 | H6: =F6*G6 -> 0.056 | I6: 0.08 | J6: 0.7 | K6: =I6*J6 -> 0.056
B7: Mid | C7: 0.06 | D7: 0.5 | E7: =D7*C7 -> 0.03 | F7: 0.1 | G7: 0.8 | H7: =F7*G7 -> 0.08 | I7: 0.1 | J7: 0.8 | K7: =I7*J7 -> 0.08
B8: High | C8: 0.08 | D8: 0.6 | E8: =D8*C8 -> 0.048 | F8: 0.14 | G8: 0.85 | H8: =F8*G8 -> 0.119 | I8: 0.14 | J8: 0.85 | K8: =I8*J8 -> 0.119
B10: DX 400-company study, Nov 2024 to Feb 2026: median PR throughput up 7.76% while AI usage rose 65%, with most orgs landing in 5-15%. Treat this as the order of magnitude for organisation-level movement, not as a check on any column here. Throughput counts pull requests while this sheet counts payroll value, so neither freed nor captured is a like-for-like comparison.

Sheet Model
B2: Budget line | C2: Year 1 | D2: Year 2 | E2: Year 3
B3: Main inputs
B4: Engineering team size, FTE | C4: =Inputs!C3 -> 300 | D4: =Inputs!C3 -> 300 | E4: =Inputs!C3 -> 300
B5: Engineering team payroll, k£ | C5: =C4*Inputs!$C$4 -> 48000 | D5: =D4*Inputs!$C$4 -> 48000 | E5: =E4*Inputs!$C$4 -> 48000
B6: Enabling team size, FTE | C6: =C4/100*Inputs!C8 -> 9 | D6: =D4/100*Inputs!C9 -> 6 | E6: =E4/100*Inputs!C9 -> 6
B7: Enabling team payroll, k£ | C7: =C6*Inputs!$C$4 -> 1440 | D7: =D6*Inputs!$C$4 -> 960 | E7: =E6*Inputs!$C$4 -> 960 | F7: From year 2 the team drops to the steady-state floor, with the rollout complete within year 1 (section 11).
B8: Tooling cost, k£ | C8: =Inputs!$C$6*Inputs!$C$3*12/1000*Inputs!$C$7/100 -> 691.2 | D8: =Inputs!$C$6*Inputs!$C$3*12/1000 -> 1152 | E8: =D8 -> 1152 | F8: Year 1 at average rollout coverage, full estate from year 2.
B9: Platform stack cost, k£ | C9: =Inputs!$C$11*Inputs!$C$7/100 -> 43.2 | D9: =Inputs!$C$11 -> 72 | E9: =D9 -> 72 | F9: AI tooling only: portal and CI/CD excluded. Year 1 at average rollout coverage.
B10: Training and hidden cost, k£ | C10: =Inputs!C12*Inputs!C3 -> 510 | D10: =Inputs!C13*Inputs!C3 -> 240 | E10: =D10 -> 240 | F10: Year 1 is the build rate; Years 2-3 is the run rate
B11: Instability adjustment, k£ | C11: =Inputs!$C$14 -> 0 | D11: =C11 -> 0 | E11: =C11 -> 0
B12: Phase 0 remediation, k£ | C12: =Inputs!C15 -> 0 | D12: 0 | E12: 0
B14: Main indicators
B15: Total cost, k£ | C15: =SUM(C7:C12) -> 2684.4 | D15: =SUM(D7:D12) -> 2424 | E15: =SUM(E7:E12) -> 2424
B16: Cost as % of payroll | C16: =C15/C5 -> 0.055925 | D16: =D15/D5 -> 0.0505 | E16: =E15/E5 -> 0.0505 | F16: A broader measure than surveyed AI budgets (DX 2026: 1-3% of the engineering budget), which count the tool invoice alone. The tooling line in this model is about 2% as well. This line adds the enabling team and training costs. The band was surveyed before agentic tools went mainstream, so treat it as a lagging floor rather than a benchmark.
B18: Scenarios
B19: Low | F19: An example of a poorly managed programme: freed capacity and conversion land low and stay there, and neither recovers on its own. Repayment needs both at the Mid case or better, and that requires a plan and hands-on management: adoption depth from section 8, booking discipline from section 9 and the section 11 gates forcing a fix-or-stop call.
B20: Value booked, k£ | C20: =C5*Scenarios!E6 -> 960 | D20: =D5*Scenarios!H6 -> 2688 | E20: =E5*Scenarios!K6 -> 2688 | F20: payroll x freed x conversion
B21: Net, k£ | C21: =C20-C$15 -> -1724.4 | D21: =D20-D$15 -> 264 | E21: =E20-E$15 -> 264 | F21: Net benefit is payroll-equivalent, priced at loaded engineering cost. What finance recognises depends on the conversion route (section 12).
B22: Cumulative, k£ | C22: =C21 -> -1724.4 | D22: =C22+D21 -> -1460.4 | E22: =D22+E21 -> -1196.4
B23: Cumulative breakeven | C23: =IF(C22>0,"Year 1",IF(D22>0,"Year 2",IF(E22>0,"Year 3","Beyond Year 3"))) -> Beyond Year 3
B25: Mid
B26: Value booked, k£ | C26: =C5*Scenarios!E7 -> 1440 | D26: =D5*Scenarios!H7 -> 3840 | E26: =E5*Scenarios!K7 -> 3840
B27: Net, k£ | C27: =C26-C$15 -> -1244.4 | D27: =D26-D$15 -> 1416 | E27: =E26-E$15 -> 1416
B28: Cumulative, k£ | C28: =C27 -> -1244.4 | D28: =C28+D27 -> 171.6 | E28: =D28+E27 -> 1587.6
B29: Cumulative breakeven | C29: =IF(C28>0,"Year 1",IF(D28>0,"Year 2",IF(E28>0,"Year 3","Beyond Year 3"))) -> Year 2
B31: High
B32: Value booked, k£ | C32: =C5*Scenarios!E8 -> 2304 | D32: =D5*Scenarios!H8 -> 5712 | E32: =E5*Scenarios!K8 -> 5712
B33: Net, k£ | C33: =C32-C$15 -> -380.4 | D33: =D32-D$15 -> 3288 | E33: =E32-E$15 -> 3288
B34: Cumulative, k£ | C34: =C33 -> -380.4 | D34: =C34+D33 -> 2907.6 | E34: =D34+E33 -> 6195.6
B35: Cumulative breakeven | C35: =IF(C34>0,"Year 1",IF(D34>0,"Year 2",IF(E34>0,"Year 3","Beyond Year 3"))) -> Year 2
B37: Sensitivity scenarios
B39: Year-2 net by conversion rate, at Mid freed capacity
C40: 0.3 | D40: 0.5 | E40: 0.7
B41: Net, year 2 | C41: =C5*Scenarios!$F$7*C40-D$15 -> -984 | D41: =D5*Scenarios!$F$7*D40-D$15 -> -24 | E41: =E5*Scenarios!$F$7*E40-D$15 -> 936
B42: Cumulative to year 2, k£ | C42: =$C$28+($C$5*Scenarios!$F$7*C40-$D$15) -> -2228.4 | D42: =$C$28+($C$5*Scenarios!$F$7*D40-$D$15) -> -1268.4 | E42: =$C$28+($C$5*Scenarios!$F$7*E40-$D$15) -> -308.4
B44: Year-2 net by tooling all-in cost ($/dev-month), at Mid | F44: The 400 in these formulas is the USD all-in baseline behind the tooling input. If that anchor changes, update the 400 here to match.
C45: 500 | D45: 600 | E45: 800
B46: Net, year 2 | C46: =$D$27-$D$8*(C45/400-1) -> 1128 | D46: =$D$27-$D$8*(D45/400-1) -> 840 | E46: =$D$27-$D$8*(E45/400-1) -> 264
B47: Cumulative to year 2, k£ | C47: =$D$28-($C$8+$D$8)*(C45/400-1) -> -289.2 | D47: =$D$28-($C$8+$D$8)*(D45/400-1) -> -750 | E47: =$D$28-($C$8+$D$8)*(E45/400-1) -> -1671.6
B48: Cumulative breakeven | C48: =IF($C$28-$C$8*(C45/400-1)>=0,"Year 1",IF($D$28-($C$8+$D$8)*(C45/400-1)>=0,"Year 2",IF($E$28-($C$8+$D$8+$E$8)*(C45/400-1)>=0,"Year 3","Beyond Year 3"))) -> Year 3 | D48: =IF($C$28-$C$8*(D45/400-1)>=0,"Year 1",IF($D$28-($C$8+$D$8)*(D45/400-1)>=0,"Year 2",IF($E$28-($C$8+$D$8+$E$8)*(D45/400-1)>=0,"Year 3","Beyond Year 3"))) -> Year 3 | E48: =IF($C$28-$C$8*(E45/400-1)>=0,"Year 1",IF($D$28-($C$8+$D$8)*(E45/400-1)>=0,"Year 2",IF($E$28-($C$8+$D$8+$E$8)*(E45/400-1)>=0,"Year 3","Beyond Year 3"))) -> Beyond Year 3

Sheet Bridge
B2: Value bridge, Mid scenario, year 2
B3: Computed from Scenarios and Model. GBP thousands.
B5: Capacity freed, value | C5: =Model!D5*Scenarios!F7 -> 4800 | D5: payroll x freed, year 2: freed time priced at fully-loaded cost | F5: =0 -> 0 | G5: =C5 -> 4800
B6: Not booked | C6: =-Model!D5*Scenarios!F7*(1-Scenarios!G7) -> -960 | D6: the unconverted share evaporates (section 9) | F6: =C5+C6 -> 3840 | G6: =-C6 -> 960
B7: Programme cost | C7: =-Model!D15 -> -2424 | D7: the five-line stack, year 2 | F7: =F6+C7 -> 1416 | G7: =-C7 -> 2424
B8: Net benefit, year 2 | C8: =SUM(C5:C7) -> 1416 | D8: matches the Model Mid net | F8: =0 -> 0 | G8: =C8 -> 1416
B10: Net benefit is payroll-equivalent, priced at loaded engineering cost. What finance recognises depends on the conversion route (Section 12)
